{"type":"Topology","objects":{"24040":{"type":"GeometryCollection","geometries":[{"type":"Polygon","properties":{"code":"2404080","name":"양산동","name_eng":"yangsan-dong","base_year":"2013"},"arcs":[[0,1,2,3,4,5,6]]},{"type":"Polygon","properties":{"code":"2404079","name":"건국동","name_eng":"Geonguk-dong","base_year":"2013"},"arcs":[[7,8,-7,9]]},{"type":"Polygon","properties":{"code":"2404078","name":"일곡동","name_eng":"Ilgok-dong","base_year":"2013"},"arcs":[[10,-1,-9,11]]},{"type":"Polygon","properties":{"code":"2404074","name":"석곡동","name_eng":"Seokgok-dong","base_year":"2013"},"arcs":[[-8,12,13,14,15,16,17,-12]]},{"type":"Polygon","properties":{"code":"2404073","name":"오치2동","name_eng":"Ochi 2(i)-dong","base_year":"2013"},"arcs":[[18,19,20,21]]},{"type":"Polygon","properties":{"code":"2404072","name":"오치1동","name_eng":"Ochi 1(il)-dong","base_year":"2013"},"arcs":[[22,23,24,-19,25]]},{"type":"Polygon","properties":{"code":"2404071","name":"매곡동","name_eng":"Maegok-dong","base_year":"2013"},"arcs":[[-21,26,27,28,-3,29]]},{"type":"Polygon","properties":{"code":"2404070","name":"삼각동","name_eng":"Samgak-dong","base_year":"2013"},"arcs":[[-11,-18,30,-26,-22,-30,-2]]},{"type":"Polygon","properties":{"code":"2404069","name":"두암3동","name_eng":"Duam 3(sam)-dong","base_year":"2013"},"arcs":[[-14,31,32,33,34]]},{"type":"Polygon","properties":{"code":"2404068","name":"두암2동","name_eng":"Duam 2(i)-dong","base_year":"2013"},"arcs":[[35,36,-15,-35,37]]},{"type":"Polygon","properties":{"code":"2404067","name":"두암1동","name_eng":"Duam 1(il)-dong","base_year":"2013"},"arcs":[[-38,-34,38,39]]},{"type":"Polygon","properties":{"code":"2404066","name":"문흥2동","name_eng":"Munheung 2(i)-dong","base_year":"2013"},"arcs":[[-24,40,41,42,43,44]]},{"type":"Polygon","properties":{"code":"2404065","name":"문흥1동","name_eng":"Munheung 1(il)-dong","base_year":"2013"},"arcs":[[-31,-17,45,-41,-23]]},{"type":"Polygon","properties":{"code":"2404064","name":"문화동","name_eng":"Munhwa-dong","base_year":"2013"},"arcs":[[-46,-16,-37,46,-42]]},{"type":"Polygon","properties":{"code":"2404063","name":"풍향동","name_eng":"Punghyang-dong","base_year":"2013"},"arcs":[[-39,-33,47,48]]},{"type":"Polygon","properties":{"code":"2404062","name":"우산동","name_eng":"Usan-dong","base_year":"2013"},"arcs":[[-36,-40,-49,49,50,51,-43,-47]]},{"type":"Polygon","properties":{"code":"2404061","name":"동림동","name_eng":"Dongnim-dong","base_year":"2013"},"arcs":[[52,53,54,-5]]},{"type":"Polygon","properties":{"code":"2404060","name":"운암3동","name_eng":"Unam 3(sam)-dong","base_year":"2013"},"arcs":[[-29,55,56,-53,-4]]},{"type":"Polygon","properties":{"code":"2404059","name":"운암2동","name_eng":"Unam 2(i)-dong","base_year":"2013"},"arcs":[[57,58,59,60,61,-56,-28]]},{"type":"Polygon","properties":{"code":"2404058","name":"운암1동","name_eng":"Unam 1(il)-dong","base_year":"2013"},"arcs":[[-57,-62,62,-54]]},{"type":"Polygon","properties":{"code":"2404057","name":"용봉동","name_eng":"Yongbong-dong","base_year":"2013"},"arcs":[[-20,-25,-45,63,64,65,-58,-27]]},{"type":"Polygon","properties":{"code":"2404056","name":"신안동","name_eng":"Sinan-dong","base_year":"2013"},"arcs":[[-66,66,67,68,69,-59]]},{"type":"Polygon","properties":{"code":"2404055","name":"임동","name_eng":"Im-dong","base_year":"2013"},"arcs":[[-60,-70,70,71]]},{"type":"Polygon","properties":{"code":"2404054","name":"중앙동","name_eng":"Jungang-dong","base_year":"2013"},"arcs":[[-69,72,73,-71]]},{"type":"Polygon","properties":{"code":"2404053","name":"중흥3동","name_eng":"Jungheung 3(sam)-dong","base_year":"2013"},"arcs":[[-52,74,75,-64,-44]]},{"type":"Polygon","properties":{"code":"2404052","name":"중흥2동","name_eng":"Jungheung 2(i)-dong","base_year":"2013"},"arcs":[[-65,-76,76,-67]]},{"type":"Polygon","properties":{"code":"2404051","name":"중흥1동","name_eng":"Jungheung 1(il)-dong","base_year":"2013"},"arcs":[[-77,-75,-51,77,-73,-68]]}]}},"arcs":[[[2788,6640],[158,-417]],[[2946,6223],[131,-382]],[[3077,5841],[-744,-575]],[[2333,5266],[-294,-36]],[[2039,5230],[-781,172]],[[1258,5402],[-279,957]],[[979,6359],[609,0],[713,530],[487,-249]],[[5269,8689],[-512,-1075],[-604,-470]],[[4153,7144],[-170,146],[-1243,-84],[48,-566]],[[979,6359],[-92,1075],[-795,136],[-92,386],[423,508],[787,209],[195,375],[639,350],[839,-223],[871,824],[1365,-518],[150,-792]],[[4199,6964],[-1253,-741]],[[4153,7144],[46,-180]],[[5269,8689],[475,-274],[522,-795],[-170,-401],[888,-1271],[-362,-500],[547,-849],[367,390],[1429,90],[804,-588],[230,-838],[-699,-858],[-24,-782],[196,-340],[-111,-991],[-625,-682],[-773,1537],[-845,-1],[-589,506],[-82,549],[-644,482]],[[5803,3073],[171,576]],[[5974,3649],[165,347]],[[6139,3996],[270,573],[-673,869]],[[5736,5438],[-160,497],[-624,-143]],[[4952,5792],[-563,553],[-190,619]],[[3689,5400],[104,-594]],[[3793,4806],[-442,233]],[[3351,5039],[22,313]],[[3373,5352],[316,48]],[[4570,5674],[-198,-667]],[[4372,5007],[-226,-246]],[[4146,4761],[-353,45]],[[3689,5400],[881,274]],[[3351,5039],[-596,-201]],[[2755,4838],[-170,-31]],[[2585,4807],[-252,459]],[[3077,5841],[296,-489]],[[4952,5792],[-382,-118]],[[5803,3073],[-455,195]],[[5348,3268],[-198,221]],[[5150,3489],[64,472]],[[5214,3961],[760,-312]],[[4846,4113],[88,379]],[[4934,4492],[1205,-496]],[[5214,3961],[-368,152]],[[5150,3489],[-536,372]],[[4614,3861],[232,252]],[[4372,5007],[509,-268]],[[4881,4739],[-207,-96]],[[4674,4643],[-235,-420]],[[4439,4223],[-140,35]],[[4299,4258],[-153,503]],[[5736,5438],[-293,91],[-308,-762],[-254,-28]],[[4934,4492],[-260,151]],[[5348,3268],[-836,212]],[[4512,3480],[102,381]],[[4512,3480],[-184,52]],[[4328,3532],[-52,20]],[[4276,3552],[163,671]],[[2039,5230],[-377,-722]],[[1662,4508],[169,-550]],[[1831,3958],[-1491,312],[835,435],[83,697]],[[2585,4807],[-267,-510]],[[2318,4297],[-656,211]],[[2755,4838],[217,-670]],[[2972,4168],[-2,-406]],[[2970,3762],[-378,-13]],[[2592,3749],[-464,187]],[[2128,3936],[190,361]],[[2128,3936],[-297,22]],[[4299,4258],[-171,-165]],[[4128,4093],[-373,-79]],[[3755,4014],[-783,154]],[[3755,4014],[48,-321]],[[3803,3693],[36,-477]],[[3839,3216],[-168,62]],[[3671,3278],[-701,484]],[[3671,3278],[-149,-443]],[[3522,2835],[-760,398],[-170,516]],[[3839,3216],[310,-268]],[[4149,2948],[-627,-113]],[[4276,3552],[-118,41]],[[4158,3593],[-30,500]],[[4158,3593],[-355,100]],[[4328,3532],[-179,-584]]],"transform":{"scale":[0.00001843618244407568,0.000014433316291251306],"translate":[126.8385854813111,35.111494733584635]}}